{
 "name": "Digitalisierungsfieber",
 "slug": "digitalisierungsfieber",
 "website": "https://andreaskunz.it/",
 "podcastIndexID": 817345,
 "rssFeed": "https://andreaskunz.libsyn.com/rss",
 "spotify": "https://open.spotify.com/show/3ByjcOlWeQxCfVwSfxn4gd",
 "description": "Digitalisierungsfieber, dem Podcast für IT Security, Datenschutz, und IT Service! Erfahren Sie, wie Sie Ihr Unternehmen sicher in das 21. Jahrhundert steuern und so bestens für die Zukunft gewappnet sind. Im Angesicht der Digitalisierung hat IT Security oberste Priorität!",
 "tags": [
  "Security",
  "Datenschutz"
 ],
 "weekly_downloads_avg": {
  "value": 0,
  "updated": ""
 },
 "episodeCount": 209,
 "latestEpisodePublished": 1689262200,
 "archive": false,
 "itunesID": 1490620957,
 "image": "images/digitalisierungsfieber.jpg"
}